setup.cfg
setup.py
twistifier/__init__.py
twistifier.egg-info/PKG-INFO
twistifier.egg-info/SOURCES.txt
twistifier.egg-info/dependency_links.txt
twistifier.egg-info/requires.txt
twistifier.egg-info/top_level.txt
twistifier/client/__init__.py
twistifier/common/__init__.py
twistifier/common/keys.py
twistifier/common/vote.py
twistifier/examples/__init__.py
twistifier/examples/default_test.py
twistifier/server/__init__.py
twistifier/server/factory.py
twistifier/server/protocol.py