Metadata-Version: 1.1
Name: twistifier
Version: 0.0.2
Summary: Twisted protocol for the Minecraft Votifier protocol
Home-page: https://github.com/gdude2002/twistifier
Author: Gareth Coles
Author-email: gdude2002@gmail.com
License: Artistic License 2.0
Platform: UNKNOWN
Requires: twisted
Requires: rsa
Requires: pyasn1
Provides: twistifier
